odoo/addons/scheduler_error_mailer/README.rst
odoo/addons/scheduler_error_mailer/__init__.py
odoo/addons/scheduler_error_mailer/__manifest__.py
odoo/addons/scheduler_error_mailer/data/ir_cron_email_tpl.xml
odoo/addons/scheduler_error_mailer/demo/ir_cron_demo.xml
odoo/addons/scheduler_error_mailer/i18n/de.po
odoo/addons/scheduler_error_mailer/i18n/es.po
odoo/addons/scheduler_error_mailer/i18n/fr.po
odoo/addons/scheduler_error_mailer/i18n/hr.po
odoo/addons/scheduler_error_mailer/i18n/pt.po
odoo/addons/scheduler_error_mailer/i18n/pt_BR.po
odoo/addons/scheduler_error_mailer/i18n/scheduler_error_mailer.pot
odoo/addons/scheduler_error_mailer/i18n/sl.po
odoo/addons/scheduler_error_mailer/i18n/zh_CN.po
odoo/addons/scheduler_error_mailer/images/scheduler_error_mailer.jpg
odoo/addons/scheduler_error_mailer/migrations/12.0.1.1.0/post-migration.py
odoo/addons/scheduler_error_mailer/migrations/12.0.1.2.0/post-migration.py
odoo/addons/scheduler_error_mailer/models/__init__.py
odoo/addons/scheduler_error_mailer/models/ir_cron.py
odoo/addons/scheduler_error_mailer/readme/CONFIGURE.rst
odoo/addons/scheduler_error_mailer/readme/CONTRIBUTORS.rst
odoo/addons/scheduler_error_mailer/readme/DESCRIPTION.rst
odoo/addons/scheduler_error_mailer/static/description/icon.png
odoo/addons/scheduler_error_mailer/static/description/index.html
odoo/addons/scheduler_error_mailer/views/ir_cron.xml
odoo12_addon_scheduler_error_mailer-12.0.1.2.0.99.dev7.dist-info/METADATA
odoo12_addon_scheduler_error_mailer-12.0.1.2.0.99.dev7.dist-info/WHEEL
odoo12_addon_scheduler_error_mailer-12.0.1.2.0.99.dev7.dist-info/top_level.txt
odoo12_addon_scheduler_error_mailer-12.0.1.2.0.99.dev7.dist-info/RECORD
